[
  {
    "id": "1748188927571",
    "content": "为什么就什么都是我的错！！之前说我不问，问了事干重了就都是我的错吗！！！\n我是没脑子，问题不经过大脑。我算是吃一堑长一智了。事情不是我干的就别继续干了，弄完了还得被说。还有。电话里话说完整，把问的信息还有接下来的行动都说完。对方同意了再行动。。。",
    "timestamp": "2025-05-25T16:02:07.571Z"
  },
  {
    "id": "1748033389483",
    "content": "看不懂代码！！！咆哮ing\n打字还老打错，明明是想成为盲打高手的说，气~~\n说真的感觉我啥都没干就想逃避，啥擅长的都没有，不是没精进就是给躲过去了，别人迎难而上逆水行舟越挫越勇，我躺平大赛怕是能得第一名的，又是废飞的一天~",
    "timestamp": "2025-05-23T20:49:49.483Z"
  },
  {
    "id": "1747322910336",
    "content": "果然第一天就是热度最高的时候，忽然上线只是想吐槽一下自己别跟猪一样吃完睡睡完吃，能好歹动一下不。另外，自学PS有点难度，今天又是什么都没做的一天，屁股坐痛了，真得起来动了。",
    "timestamp": "2025-05-15T15:28:30.336Z"
  },
  {
    "id": "1747305704117",
    "content": "竟然真的有一个可以记录我碎碎念的地方，不是没尝试过日记，但三分钟的热度确实很难维持住，虽然很大部分原因一定是我嫌弃自己写的字，果然还是键盘的敲击声最悦耳了。\n昨晚在想象可以在古早版的微博抒发己见，事实是那时的我接触最多的电子产品应该是点读笔了。在这里公开记录很显然没有私密性可言，却莫名令我感到愉悦，就像在人来人往中未曾注意到我，我是亲历者，却又自以为站在上帝视角。\n睡前总是辗转难眠，因为在脑海里过了不止365个人生，刚发现蛆写的李姐的混蛋超能力世界，好看，好看到想骂自己混蛋，作者混蛋，世界就是一个大混蛋。烂柯棋缘也不错，因为主角装着我想装的B。\n不想坚持写什么，想到什么写什么，想不到就不写\n总有灵光一现的画面，在我大脑中的相机里，配着应景的ost，说着自我感动的对白，有时候感觉——\n\n\n做我的大脑好累啊！！！丫的每次自己拍完了一部电影，光颅内高潮有意思吗、怎么会有人意识流的开派对k歌劲舞，身体能毫不表露的，受不了了，毁灭吧地球",
    "timestamp": "2025-05-15T10:41:44.117Z"
  }
]